{"status":"FAIL","msg":"FAIL:\n Uncaught: { message: \"#1.2: var __obj = {toString: function() {return new Object();}, valueOf: function() {return 1;}}; String(__obj) === \"1\". Actual: Test262Error: #1.1: var __obj = {toString: function() {return new Object();}, valueOf: function() {return 1;}}; String(__obj) === \"1\". Actual: [object Object]\" }\n    at ../../test262/test/built-ins/String/S8.12.8_A2.js:32\n\n","path":"../../test262/test/built-ins/String/S8.12.8_A2.js","memory_kb":0,"duration":3355652346}