{"status":"FAIL","msg":"FAIL:\n Uncaught: { \"name\": \"Test262Error\", \"message\": \"Actual [get options.disambiguation, get options.disambiguation.toString, call options.disambiguation.toString, get options.offsetDisambiguation, get options.overflow, get options.overflow.toString, call options.overflow.toString, get item.calendar, get item.era, get item.eraYear, get item.year, get item.year.valueOf, call item.year.valueOf, get item.month, get item.month.valueOf, call item.month.valueOf, get item.monthCode, get item.monthCode.toString, call item.monthCode.toString, get item.day, get item.day.valueOf, call item.day.valueOf, get item.hour, get item.hour.valueOf, call item.hour.valueOf, get item.minute, get item.minute.valueOf, call item.minute.valueOf, get item.second, get item.second.valueOf, call item.second.valueOf, get item.millisecond, get item.millisecond.valueOf, call item.millisecond.valueOf, get item.microsecond, get item.microsecond.valueOf, call item.microsecond.valueOf, get item.nanosecond, get item.nanosecond.valueOf, call item.nanosecond.valueOf, get item.timeZone, get item.offset, get item.offset.toString, call item.offset.toString] and expected [get item.calendar, get item.day, get item.day.valueOf, call item.day.valueOf, get item.hour, get item.hour.valueOf, call item.hour.valueOf, get item.microsecond, get item.microsecond.valueOf, call item.microsecond.valueOf, get item.millisecond, get item.millisecond.valueOf, call item.millisecond.valueOf, get item.minute, get item.minute.valueOf, call item.minute.valueOf, get item.month, get item.month.valueOf, call item.month.valueOf, get item.monthCode, get item.monthCode.toString, call item.monthCode.toString, get item.nanosecond, get item.nanosecond.valueOf, call item.nanosecond.valueOf, get item.offset, get item.offset.toString, call item.offset.toString, get item.second, get item.second.valueOf, call item.second.valueOf, get item.timeZone, get item.year, get item.year.valueOf, call item.year.valueOf, get options.disambiguation, get options.disambiguation.toString, call options.disambiguation.toString, get options.offset, get options.offset.toString, call options.offset.toString, get options.overflow, get options.overflow.toString, call options.overflow.toString] should have the same contents. order of operations\" }\n    at assert (../../test262/harness/assert.js:18)\n    at ../../test262/harness/assert.js:124\n    at ../../test262/test/built-ins/Temporal/ZonedDateTime/from/order-of-operations.js:94\n\n","path":"../../test262/test/built-ins/Temporal/ZonedDateTime/from/order-of-operations.js","memory_kb":0,"duration":275256213}